{
  "images": {
    "background": "https://images.koji-cdn.com/151903f0-b74a-4065-812c-da0a4cc137c0/32mry-7a6e35800ba74edab0d4387512e3df84.png?defaultSource=camera"
  },
  "@@editor": [
    {
      "key": "images",
      "name": "Images",
      "icon": "📚",
      "source": "images.json",
      "fields": [
        {
          "key": "background",
          "name": "Change photo",
          "description": "Take a selfie or upload a picture",
          "icon": "📸",
          "type": "image"
        }
      ]
    }
  ]
}